zaicore/__init__.py
zaicore/__main__.py
zaicore/analytics.py
zaicore/core.py
zaicore/network.py
zaicore/reasoning.py
zaicore/plugins/__init__.py
zaicore/plugins/websearch_connector.py
zaicore-0.2.4.dist-info/licenses/LICENSE
zaicore-0.2.4.dist-info/METADATA
zaicore-0.2.4.dist-info/WHEEL
zaicore-0.2.4.dist-info/top_level.txt
zaicore-0.2.4.dist-info/RECORD
