Metadata-Version: 2.4
Name: zaicore
Version: 0.2.4
Summary: ZAI Core — Adaptive Intelligence with auto-learn, insights, persistent & networked memory
Home-page: https://github.com/muhammadzaidanf/ZAI-Core
Author: Muhammad Zaidan
Author-email: muhammadzaidanfaiz8@gmail.com
Classifier: Programming Language :: Python :: 3
Classifier: License :: OSI Approved :: MIT License
Classifier: Operating System :: OS Independent
Classifier: Topic :: Scientific/Engineering :: Artificial Intelligence
Classifier: Intended Audience :: Developers
Requires-Python: >=3.8
License-File: LICENSE
Requires-Dist: requests>=2.25
Dynamic: author
Dynamic: author-email
Dynamic: classifier
Dynamic: description
Dynamic: description-content-type
Dynamic: home-page
Dynamic: license-file
Dynamic: requires-dist
Dynamic: requires-python
Dynamic: summary
